{
    "fileFormatVersion": "1",
    "parameterSets": {
        "New set 1": {
            "Braille_location": "above opening",
            "Braille_size_multiplier": "10",
            "Braille_text": "",
            "Braille_to_opening_distance": "5",
            "add_circular_opening": "yes",
            "add_mini_tabs": "no",
            "add_symmetric_openings": "no",
            "approx_dovetail_width": "4",
            "bar_corner_radius": "2",
            "bar_edge_slope": "90",
            "bottom_edge_compensation_for_tight_cases": "0",
            "bottom_of_status_bar": "0",
            "bottom_of_upper_command_bar": "0",
            "bottom_of_upper_message_bar": "0",
            "bottom_padding": "0",
            "case_height": "220",
            "case_opening_corner_radius": "5",
            "case_thickness": "15",
            "case_to_screen_depth": "5",
            "case_width": "275",
            "cell_bottom_edge_slope": "90",
            "cell_corner_radius": "3",
            "cell_diameter": "15",
            "cell_edge_chamfer": "0.69999999999999996",
            "cell_edge_slope": "90",
            "cell_height": "25",
            "cell_shape": "rectangular",
            "cell_top_edge_slope": "90",
            "cell_width": "25",
            "clip_bottom_length": "35",
            "clip_locations": "vertical only",
            "cut_out_screen": "no",
            "diameter_of_opening": "10",
            "distance_between_horizontal_clips": "60",
            "distance_between_horizontal_slide_in_tabs": "60",
            "distance_between_raised_tabs": "60",
            "distance_between_vertical_clips": "40",
            "distance_between_vertical_slide_in_tabs": "60",
            "embed_magnets": "yes",
            "engraved_text": "",
            "expose_ambient_light_sensors": "yes",
            "expose_camera": "yes",
            "expose_home_button": "yes",
            "expose_lower_command_bar": "no",
            "expose_lower_message_bar": "no",
            "expose_status_bar": "no",
            "expose_upper_command_bar": "no",
            "expose_upper_message_bar": "no",
            "first_two_layers_only": "no",
            "font_style": "normal",
            "generate": "keyguard",
            "have_a_case": "yes",
            "have_a_keyguard_frame": "no",
            "height_of_opening_in_case": "0",
            "height_of_ridge": "2",
            "home_button_edge_slope": "30",
            "horizontal_clip_width": "20",
            "horizontal_rail_width": "5",
            "horizontal_slide_in_tab_length": "4",
            "horizontal_slide_in_tab_width": "20",
            "include_screenshot": "no",
            "insert_recess": "0",
            "insert_tightness_of_fit": "0",
            "keyguard_corner_radius": "2",
            "keyguard_display_angle": "0",
            "keyguard_edge_chamfer": "0.69999999999999996",
            "keyguard_frame_thickness": "5",
            "keyguard_height": "160",
            "keyguard_horizontal_tightness_of_fit": "0",
            "keyguard_location": "top surface",
            "keyguard_region": "screen region",
            "keyguard_thickness": "4",
            "keyguard_vertical_tightness_of_fit": "0",
            "keyguard_width": "210",
            "left_edge_compensation_for_tight_cases": "0",
            "left_padding": "0",
            "lower_command_bar_height": "0",
            "lower_message_bar_height": "0",
            "magnet_size": "20 x 8 x 1.5",
            "mini_tab_height": "1",
            "mini_tab_inset_distance": "20",
            "mini_tab_length": "2",
            "mini_tab_width": "10",
            "mount_keyguard_with": "snap-in tabs",
            "mount_to_top_of_opening_distance": "5",
            "mounting_method": "Raised Tabs",
            "move_screenshot_horizontally": "0",
            "move_screenshot_vertically": "0",
            "notch_in_post": "yes",
            "number_of_columns": "4",
            "number_of_rows": "3",
            "orientation": "landscape",
            "post_diameter": "4",
            "post_length": "5",
            "post_tightness_of_fit": "0",
            "preferred_rail_height": "4",
            "preferred_raised_tab_thickness": "3",
            "preferred_slide_in_tab_thickness": "2",
            "rail_slope": "90",
            "raised_tab_height": "6",
            "raised_tab_length": "8",
            "raised_tab_width": "20",
            "ramp_angle": "30",
            "right_edge_compensation_for_tight_cases": "0",
            "right_padding": "0",
            "screen_area_thickness": "4",
            "shelf_depth": "3",
            "shelf_thickness": "2",
            "show_back_of_keyguard": "no",
            "slide_horizontally": "0",
            "slide_in_tab_locations": "horizontal only",
            "slide_vertically": "0",
            "smoothness_of_circles_and_arcs": "40",
            "snap_in_tab_on_bottom_edge_of_keyguard": "yes",
            "snap_in_tab_on_top_edge_of_keyguard": "no",
            "split_line": "0",
            "split_line_location": "0",
            "split_line_type": "flat",
            "starting_corner_for_screen_measurements": "upper-left",
            "starting_height": "0",
            "status_bar_height": "0",
            "swap_camera_and_home_button": "no",
            "text": "",
            "text_angle": "horizontal",
            "text_depth": "-2",
            "text_height": "5",
            "text_horizontal_alignment": "center",
            "text_vertical_alignment": "center",
            "thickness_of_ridge": "2",
            "tightness_of_dovetail_joint": "5",
            "top_edge_compensation_for_tight_cases": "0",
            "top_of_lower_command_bar": "0",
            "top_of_lower_message_bar": "0",
            "top_padding": "0",
            "trim_to_screen": "no",
            "type_of_keyguard": "3D-Printed",
            "type_of_tablet": "iPad 9th generation",
            "unequal_bottom_side_of_case": "0",
            "unequal_bottom_side_of_case_opening": "0",
            "unequal_left_side_of_case": "0",
            "unequal_left_side_of_case_opening": "0",
            "unit_of_measure_for_screen": "px",
            "upper_command_bar_height": "0",
            "upper_message_bar_height": "0",
            "use_Laser_Cutting_best_practices": "yes",
            "velcro_size": "1",
            "vertical_clip_width": "20",
            "vertical_rail_width": "5",
            "vertical_slide_in_tab_length": "4",
            "vertical_slide_in_tab_width": "20",
            "width_of_opening_in_case": "0"
        },
        "New set 2": {
            "Braille_location": "above opening",
            "Braille_size_multiplier": "10",
            "Braille_text": "",
            "Braille_to_opening_distance": "5",
            "add_circular_opening": "yes",
            "add_mini_tabs": "no",
            "add_symmetric_openings": "no",
            "approx_dovetail_width": "4",
            "bar_corner_radius": "2",
            "bar_edge_slope": "90",
            "bottom_edge_compensation_for_tight_cases": "0",
            "bottom_of_status_bar": "0",
            "bottom_of_upper_command_bar": "0",
            "bottom_of_upper_message_bar": "0",
            "bottom_padding": "0",
            "case_height": "220",
            "case_opening_corner_radius": "5",
            "case_thickness": "15",
            "case_to_screen_depth": "5",
            "case_width": "275",
            "cell_bottom_edge_slope": "90",
            "cell_corner_radius": "3",
            "cell_diameter": "15",
            "cell_edge_chamfer": "0.69999999999999996",
            "cell_edge_slope": "90",
            "cell_height": "25",
            "cell_shape": "rectangular",
            "cell_top_edge_slope": "90",
            "cell_width": "25",
            "clip_bottom_length": "35",
            "clip_locations": "horizontal only",
            "cut_out_screen": "no",
            "diameter_of_opening": "10",
            "distance_between_horizontal_clips": "60",
            "distance_between_horizontal_slide_in_tabs": "60",
            "distance_between_raised_tabs": "60",
            "distance_between_vertical_clips": "40",
            "distance_between_vertical_slide_in_tabs": "60",
            "embed_magnets": "no",
            "engraved_text": "",
            "expose_ambient_light_sensors": "yes",
            "expose_camera": "yes",
            "expose_home_button": "yes",
            "expose_lower_command_bar": "no",
            "expose_lower_message_bar": "no",
            "expose_status_bar": "no",
            "expose_upper_command_bar": "no",
            "expose_upper_message_bar": "no",
            "first_two_layers_only": "no",
            "font_style": "normal",
            "generate": "keyguard frame",
            "have_a_case": "yes",
            "have_a_keyguard_frame": "no",
            "height_of_opening_in_case": "175",
            "height_of_ridge": "2",
            "home_button_edge_slope": "30",
            "horizontal_clip_width": "20",
            "horizontal_rail_width": "5",
            "horizontal_slide_in_tab_length": "4",
            "horizontal_slide_in_tab_width": "20",
            "include_screenshot": "no",
            "insert_recess": "0",
            "insert_tightness_of_fit": "0",
            "keyguard_corner_radius": "2",
            "keyguard_display_angle": "0",
            "keyguard_edge_chamfer": "0.69999999999999996",
            "keyguard_frame_thickness": "5",
            "keyguard_height": "160",
            "keyguard_horizontal_tightness_of_fit": "0",
            "keyguard_location": "top surface",
            "keyguard_region": "screen region",
            "keyguard_thickness": "4",
            "keyguard_vertical_tightness_of_fit": "0",
            "keyguard_width": "210",
            "left_edge_compensation_for_tight_cases": "0",
            "left_padding": "0",
            "lower_command_bar_height": "0",
            "lower_message_bar_height": "0",
            "magnet_size": "20 x 8 x 1.5",
            "mini_tab_height": "1",
            "mini_tab_inset_distance": "20",
            "mini_tab_length": "2",
            "mini_tab_width": "10",
            "mount_keyguard_with": "snap-in tabs",
            "mount_to_top_of_opening_distance": "5",
            "mounting_method": "Raised Tabs",
            "move_screenshot_horizontally": "0",
            "move_screenshot_vertically": "0",
            "notch_in_post": "yes",
            "number_of_columns": "4",
            "number_of_rows": "3",
            "orientation": "landscape",
            "post_diameter": "4",
            "post_length": "5",
            "post_tightness_of_fit": "0",
            "preferred_rail_height": "4",
            "preferred_raised_tab_thickness": "2",
            "preferred_slide_in_tab_thickness": "2",
            "rail_slope": "90",
            "raised_tab_height": "6",
            "raised_tab_length": "8",
            "raised_tab_width": "20",
            "ramp_angle": "30",
            "right_edge_compensation_for_tight_cases": "0",
            "right_padding": "0",
            "screen_area_thickness": "4",
            "shelf_depth": "3",
            "shelf_thickness": "2",
            "show_back_of_keyguard": "no",
            "slide_horizontally": "0",
            "slide_in_tab_locations": "horizontal only",
            "slide_vertically": "0",
            "smoothness_of_circles_and_arcs": "40",
            "snap_in_tab_on_bottom_edge_of_keyguard": "no",
            "snap_in_tab_on_top_edge_of_keyguard": "no",
            "split_line": "0",
            "split_line_location": "0",
            "split_line_type": "flat",
            "starting_corner_for_screen_measurements": "upper-left",
            "starting_height": "0",
            "status_bar_height": "0",
            "swap_camera_and_home_button": "no",
            "text": "",
            "text_angle": "horizontal",
            "text_depth": "-2",
            "text_height": "5",
            "text_horizontal_alignment": "center",
            "text_vertical_alignment": "center",
            "thickness_of_ridge": "2",
            "tightness_of_dovetail_joint": "5",
            "top_edge_compensation_for_tight_cases": "0",
            "top_of_lower_command_bar": "0",
            "top_of_lower_message_bar": "0",
            "top_padding": "0",
            "trim_to_screen": "no",
            "type_of_keyguard": "3D-Printed",
            "type_of_tablet": "iPad 9th generation",
            "unequal_bottom_side_of_case": "0",
            "unequal_bottom_side_of_case_opening": "0",
            "unequal_left_side_of_case": "0",
            "unequal_left_side_of_case_opening": "0",
            "unit_of_measure_for_screen": "px",
            "upper_command_bar_height": "0",
            "upper_message_bar_height": "0",
            "use_Laser_Cutting_best_practices": "yes",
            "velcro_size": "1",
            "vertical_clip_width": "20",
            "vertical_rail_width": "5",
            "vertical_slide_in_tab_length": "4",
            "vertical_slide_in_tab_width": "20",
            "width_of_opening_in_case": "245"
        },
        "New set 3": {
            "Braille_location": "above opening",
            "Braille_size_multiplier": "10",
            "Braille_text": "",
            "Braille_to_opening_distance": "5",
            "add_circular_opening": "yes",
            "add_mini_tabs": "no",
            "add_symmetric_openings": "no",
            "approx_dovetail_width": "4",
            "bar_corner_radius": "2",
            "bar_edge_slope": "90",
            "bottom_edge_compensation_for_tight_cases": "0",
            "bottom_of_status_bar": "0",
            "bottom_of_upper_command_bar": "0",
            "bottom_of_upper_message_bar": "0",
            "bottom_padding": "0",
            "case_height": "220",
            "case_opening_corner_radius": "5",
            "case_thickness": "15",
            "case_to_screen_depth": "5",
            "case_width": "275",
            "cell_bottom_edge_slope": "90",
            "cell_corner_radius": "3",
            "cell_diameter": "15",
            "cell_edge_chamfer": "0.69999999999999996",
            "cell_edge_slope": "90",
            "cell_height": "56",
            "cell_shape": "rectangular",
            "cell_top_edge_slope": "90",
            "cell_width": "87",
            "clip_bottom_length": "35",
            "clip_locations": "horizontal only",
            "cut_out_screen": "no",
            "diameter_of_opening": "10",
            "distance_between_horizontal_clips": "60",
            "distance_between_horizontal_slide_in_tabs": "60",
            "distance_between_raised_tabs": "45",
            "distance_between_vertical_clips": "40",
            "distance_between_vertical_slide_in_tabs": "60",
            "embed_magnets": "no",
            "engraved_text": "",
            "expose_ambient_light_sensors": "yes",
            "expose_camera": "yes",
            "expose_home_button": "yes",
            "expose_lower_command_bar": "no",
            "expose_lower_message_bar": "no",
            "expose_status_bar": "no",
            "expose_upper_command_bar": "no",
            "expose_upper_message_bar": "no",
            "first_two_layers_only": "no",
            "font_style": "normal",
            "generate": "keyguard",
            "have_a_case": "yes",
            "have_a_keyguard_frame": "no",
            "height_of_opening_in_case": "160",
            "height_of_ridge": "2",
            "home_button_edge_slope": "30",
            "horizontal_clip_width": "20",
            "horizontal_rail_width": "5",
            "horizontal_slide_in_tab_length": "4",
            "horizontal_slide_in_tab_width": "20",
            "include_screenshot": "yes",
            "insert_recess": "0",
            "insert_tightness_of_fit": "0",
            "keyguard_corner_radius": "2",
            "keyguard_display_angle": "0",
            "keyguard_edge_chamfer": "0.69999999999999996",
            "keyguard_frame_thickness": "5",
            "keyguard_height": "178",
            "keyguard_horizontal_tightness_of_fit": "0",
            "keyguard_location": "top surface",
            "keyguard_region": "screen region",
            "keyguard_thickness": "4",
            "keyguard_vertical_tightness_of_fit": "0",
            "keyguard_width": "210",
            "left_edge_compensation_for_tight_cases": "0",
            "left_padding": "9",
            "lower_command_bar_height": "0",
            "lower_message_bar_height": "0",
            "magnet_size": "20 x 8 x 1.5",
            "mini_tab_height": "1",
            "mini_tab_inset_distance": "20",
            "mini_tab_length": "2",
            "mini_tab_width": "10",
            "mount_keyguard_with": "snap-in tabs",
            "mount_to_top_of_opening_distance": "5",
            "mounting_method": "Raised Tabs",
            "move_screenshot_horizontally": "0",
            "move_screenshot_vertically": "0",
            "notch_in_post": "yes",
            "number_of_columns": "2",
            "number_of_rows": "2",
            "orientation": "landscape",
            "post_diameter": "4",
            "post_length": "5",
            "post_tightness_of_fit": "0",
            "preferred_rail_height": "4",
            "preferred_raised_tab_thickness": "3",
            "preferred_slide_in_tab_thickness": "2",
            "rail_slope": "90",
            "raised_tab_height": "5",
            "raised_tab_length": "25",
            "raised_tab_width": "23",
            "ramp_angle": "45",
            "right_edge_compensation_for_tight_cases": "0",
            "right_padding": "9",
            "screen_area_thickness": "4",
            "shelf_depth": "3",
            "shelf_thickness": "2",
            "show_back_of_keyguard": "no",
            "slide_horizontally": "0",
            "slide_in_tab_locations": "horizontal only",
            "slide_vertically": "0",
            "smoothness_of_circles_and_arcs": "40",
            "snap_in_tab_on_bottom_edge_of_keyguard": "yes",
            "snap_in_tab_on_top_edge_of_keyguard": "yes",
            "split_line": "0",
            "split_line_location": "0",
            "split_line_type": "flat",
            "starting_corner_for_screen_measurements": "upper-left",
            "starting_height": "0",
            "status_bar_height": "0",
            "swap_camera_and_home_button": "no",
            "text": "",
            "text_angle": "horizontal",
            "text_depth": "-2",
            "text_height": "5",
            "text_horizontal_alignment": "center",
            "text_vertical_alignment": "center",
            "thickness_of_ridge": "2",
            "tightness_of_dovetail_joint": "5",
            "top_edge_compensation_for_tight_cases": "0",
            "top_of_lower_command_bar": "0",
            "top_of_lower_message_bar": "0",
            "top_padding": "0",
            "trim_to_screen": "no",
            "type_of_keyguard": "3D-Printed",
            "type_of_tablet": "iPad Pro 11-inch 2nd Generation",
            "unequal_bottom_side_of_case": "0",
            "unequal_bottom_side_of_case_opening": "0",
            "unequal_left_side_of_case": "0",
            "unequal_left_side_of_case_opening": "0",
            "unit_of_measure_for_screen": "px",
            "upper_command_bar_height": "0",
            "upper_message_bar_height": "24",
            "use_Laser_Cutting_best_practices": "yes",
            "use_velcro_dots": "yes",
            "velcro_size": "2",
            "vertical_clip_width": "20",
            "vertical_rail_width": "5",
            "vertical_slide_in_tab_length": "4",
            "vertical_slide_in_tab_width": "20",
            "width_of_opening_in_case": "230"
        },
        "New set 4": {
            "Braille_location": "above opening",
            "Braille_size_multiplier": "10",
            "Braille_text": "",
            "Braille_to_opening_distance": "5",
            "add_circular_opening": "yes",
            "add_mini_tabs": "no",
            "add_symmetric_openings": "no",
            "approx_dovetail_width": "4",
            "bar_corner_radius": "2",
            "bar_edge_slope": "90",
            "bottom_edge_compensation_for_tight_cases": "0",
            "bottom_of_status_bar": "0",
            "bottom_of_upper_command_bar": "0",
            "bottom_of_upper_message_bar": "0",
            "bottom_padding": "0",
            "case_height": "220",
            "case_opening_corner_radius": "5",
            "case_thickness": "15",
            "case_to_screen_depth": "5",
            "case_width": "275",
            "cell_bottom_edge_slope": "90",
            "cell_corner_radius": "3",
            "cell_diameter": "15",
            "cell_edge_chamfer": "0.69999999999999996",
            "cell_edge_slope": "90",
            "cell_height": "25",
            "cell_shape": "rectangular",
            "cell_top_edge_slope": "90",
            "cell_width": "25",
            "clip_bottom_length": "35",
            "clip_locations": "horizontal only",
            "cut_out_screen": "no",
            "diameter_of_opening": "10",
            "distance_between_horizontal_clips": "60",
            "distance_between_horizontal_slide_in_tabs": "60",
            "distance_between_raised_tabs": "60",
            "distance_between_vertical_clips": "40",
            "distance_between_vertical_slide_in_tabs": "60",
            "embed_magnets": "no",
            "engraved_text": "",
            "expose_ambient_light_sensors": "yes",
            "expose_camera": "yes",
            "expose_home_button": "yes",
            "expose_lower_command_bar": "no",
            "expose_lower_message_bar": "no",
            "expose_status_bar": "no",
            "expose_upper_command_bar": "no",
            "expose_upper_message_bar": "no",
            "first_two_layers_only": "no",
            "font_style": "normal",
            "generate": "keyguard",
            "have_a_case": "yes",
            "have_a_keyguard_frame": "no",
            "height_of_opening_in_case": "175",
            "height_of_ridge": "2",
            "home_button_edge_slope": "30",
            "horizontal_clip_width": "20",
            "horizontal_rail_width": "5",
            "horizontal_slide_in_tab_length": "4",
            "horizontal_slide_in_tab_width": "20",
            "include_screenshot": "yes",
            "insert_recess": "0",
            "insert_tightness_of_fit": "0",
            "keyguard_corner_radius": "2",
            "keyguard_display_angle": "0",
            "keyguard_edge_chamfer": "0.69999999999999996",
            "keyguard_frame_thickness": "5",
            "keyguard_height": "160",
            "keyguard_horizontal_tightness_of_fit": "0",
            "keyguard_location": "top surface",
            "keyguard_region": "screen region",
            "keyguard_thickness": "4",
            "keyguard_vertical_tightness_of_fit": "0",
            "keyguard_width": "210",
            "left_edge_compensation_for_tight_cases": "0",
            "left_padding": "0",
            "lower_command_bar_height": "0",
            "lower_message_bar_height": "0",
            "magnet_size": "20 x 8 x 1.5",
            "mini_tab_height": "1",
            "mini_tab_inset_distance": "20",
            "mini_tab_length": "2",
            "mini_tab_width": "10",
            "mount_keyguard_with": "snap-in tabs",
            "mount_to_top_of_opening_distance": "5",
            "mounting_method": "No Mount",
            "move_screenshot_horizontally": "0",
            "move_screenshot_vertically": "0",
            "notch_in_post": "yes",
            "number_of_columns": "4",
            "number_of_rows": "3",
            "orientation": "landscape",
            "post_diameter": "4",
            "post_length": "5",
            "post_tightness_of_fit": "0",
            "preferred_rail_height": "4",
            "preferred_raised_tab_thickness": "2",
            "preferred_slide_in_tab_thickness": "2",
            "rail_slope": "90",
            "raised_tab_height": "6",
            "raised_tab_length": "8",
            "raised_tab_width": "20",
            "ramp_angle": "30",
            "right_edge_compensation_for_tight_cases": "0",
            "right_padding": "0",
            "screen_area_thickness": "4",
            "shelf_depth": "3",
            "shelf_thickness": "2",
            "show_back_of_keyguard": "no",
            "slide_horizontally": "0",
            "slide_in_tab_locations": "horizontal only",
            "slide_vertically": "0",
            "smoothness_of_circles_and_arcs": "40",
            "snap_in_tab_on_bottom_edge_of_keyguard": "yes",
            "snap_in_tab_on_top_edge_of_keyguard": "yes",
            "split_line": "0",
            "split_line_location": "0",
            "split_line_type": "flat",
            "starting_corner_for_screen_measurements": "upper-left",
            "starting_height": "0",
            "status_bar_height": "0",
            "swap_camera_and_home_button": "no",
            "text": "",
            "text_angle": "horizontal",
            "text_depth": "-2",
            "text_height": "5",
            "text_horizontal_alignment": "center",
            "text_vertical_alignment": "center",
            "thickness_of_ridge": "2",
            "tightness_of_dovetail_joint": "5",
            "top_edge_compensation_for_tight_cases": "0",
            "top_of_lower_command_bar": "0",
            "top_of_lower_message_bar": "0",
            "top_padding": "0",
            "trim_to_screen": "no",
            "type_of_keyguard": "3D-Printed",
            "type_of_tablet": "iPad 9th generation",
            "unequal_bottom_side_of_case": "0",
            "unequal_bottom_side_of_case_opening": "0",
            "unequal_left_side_of_case": "0",
            "unequal_left_side_of_case_opening": "0",
            "unit_of_measure_for_screen": "px",
            "upper_command_bar_height": "0",
            "upper_message_bar_height": "0",
            "use_Laser_Cutting_best_practices": "yes",
            "use_velcro_dots": "no",
            "velcro_size": "1",
            "vertical_clip_width": "20",
            "vertical_rail_width": "5",
            "vertical_slide_in_tab_length": "4",
            "vertical_slide_in_tab_width": "20",
            "width_of_opening_in_case": "245"
        },
        "Ipad pro 4 grid dots": {
            "Braille_location": "above opening",
            "Braille_size_multiplier": "10",
            "Braille_text": "",
            "Braille_to_opening_distance": "5",
            "add_circular_opening": "yes",
            "add_mini_tabs": "no",
            "add_symmetric_openings": "no",
            "approx_dovetail_width": "4",
            "bar_corner_radius": "2",
            "bar_edge_slope": "90",
            "bottom_edge_compensation_for_tight_cases": "0",
            "bottom_of_status_bar": "0",
            "bottom_of_upper_command_bar": "0",
            "bottom_of_upper_message_bar": "0",
            "bottom_padding": "0",
            "case_height": "220",
            "case_opening_corner_radius": "5",
            "case_thickness": "15",
            "case_to_screen_depth": "5",
            "case_width": "275",
            "cell_bottom_edge_slope": "90",
            "cell_corner_radius": "3",
            "cell_diameter": "15",
            "cell_edge_chamfer": "0.69999999999999996",
            "cell_edge_slope": "90",
            "cell_height": "56",
            "cell_shape": "rectangular",
            "cell_top_edge_slope": "90",
            "cell_width": "87",
            "clip_bottom_length": "35",
            "clip_locations": "horizontal only",
            "cut_out_screen": "no",
            "diameter_of_opening": "10",
            "distance_between_horizontal_clips": "60",
            "distance_between_horizontal_slide_in_tabs": "60",
            "distance_between_raised_tabs": "45",
            "distance_between_vertical_clips": "40",
            "distance_between_vertical_slide_in_tabs": "60",
            "embed_magnets": "no",
            "engraved_text": "",
            "expose_ambient_light_sensors": "yes",
            "expose_camera": "yes",
            "expose_home_button": "yes",
            "expose_lower_command_bar": "no",
            "expose_lower_message_bar": "no",
            "expose_status_bar": "no",
            "expose_upper_command_bar": "no",
            "expose_upper_message_bar": "no",
            "first_two_layers_only": "no",
            "font_style": "normal",
            "generate": "keyguard",
            "have_a_case": "yes",
            "have_a_keyguard_frame": "no",
            "height_of_opening_in_case": "160",
            "height_of_ridge": "2",
            "home_button_edge_slope": "30",
            "horizontal_clip_width": "20",
            "horizontal_rail_width": "5",
            "horizontal_slide_in_tab_length": "4",
            "horizontal_slide_in_tab_width": "20",
            "include_screenshot": "no",
            "insert_recess": "0",
            "insert_tightness_of_fit": "0",
            "keyguard_corner_radius": "2",
            "keyguard_display_angle": "0",
            "keyguard_edge_chamfer": "0.69999999999999996",
            "keyguard_frame_thickness": "5",
            "keyguard_height": "178",
            "keyguard_horizontal_tightness_of_fit": "0",
            "keyguard_location": "top surface",
            "keyguard_region": "screen region",
            "keyguard_thickness": "4",
            "keyguard_vertical_tightness_of_fit": "0",
            "keyguard_width": "210",
            "left_edge_compensation_for_tight_cases": "0",
            "left_padding": "9",
            "lower_command_bar_height": "0",
            "lower_message_bar_height": "0",
            "magnet_size": "20 x 8 x 1.5",
            "mini_tab_height": "1",
            "mini_tab_inset_distance": "20",
            "mini_tab_length": "2",
            "mini_tab_width": "10",
            "mount_keyguard_with": "snap-in tabs",
            "mount_to_top_of_opening_distance": "5",
            "mounting_method": "Raised Tabs",
            "move_screenshot_horizontally": "0",
            "move_screenshot_vertically": "0",
            "notch_in_post": "yes",
            "number_of_columns": "2",
            "number_of_rows": "2",
            "orientation": "landscape",
            "post_diameter": "4",
            "post_length": "5",
            "post_tightness_of_fit": "0",
            "preferred_rail_height": "4",
            "preferred_raised_tab_thickness": "3",
            "preferred_slide_in_tab_thickness": "2",
            "rail_slope": "90",
            "raised_tab_height": "5",
            "raised_tab_length": "25",
            "raised_tab_width": "23",
            "ramp_angle": "45",
            "right_edge_compensation_for_tight_cases": "0",
            "right_padding": "9",
            "screen_area_thickness": "4",
            "shelf_depth": "3",
            "shelf_thickness": "2",
            "show_back_of_keyguard": "no",
            "slide_horizontally": "0",
            "slide_in_tab_locations": "horizontal only",
            "slide_vertically": "0",
            "smoothness_of_circles_and_arcs": "40",
            "snap_in_tab_on_bottom_edge_of_keyguard": "yes",
            "snap_in_tab_on_top_edge_of_keyguard": "yes",
            "split_line": "0",
            "split_line_location": "0",
            "split_line_type": "flat",
            "starting_corner_for_screen_measurements": "upper-left",
            "starting_height": "0",
            "status_bar_height": "0",
            "swap_camera_and_home_button": "no",
            "text": "",
            "text_angle": "horizontal",
            "text_depth": "-2",
            "text_height": "5",
            "text_horizontal_alignment": "center",
            "text_vertical_alignment": "center",
            "thickness_of_ridge": "2",
            "tightness_of_dovetail_joint": "5",
            "top_edge_compensation_for_tight_cases": "0",
            "top_of_lower_command_bar": "0",
            "top_of_lower_message_bar": "0",
            "top_padding": "0",
            "trim_to_screen": "no",
            "type_of_keyguard": "3D-Printed",
            "type_of_tablet": "iPad Pro 11-inch 2nd Generation",
            "unequal_bottom_side_of_case": "0",
            "unequal_bottom_side_of_case_opening": "0",
            "unequal_left_side_of_case": "0",
            "unequal_left_side_of_case_opening": "0",
            "unit_of_measure_for_screen": "px",
            "upper_command_bar_height": "0",
            "upper_message_bar_height": "24",
            "use_Laser_Cutting_best_practices": "yes",
            "use_velcro_dots": "yes",
            "velcro_size": "2",
            "vertical_clip_width": "20",
            "vertical_rail_width": "5",
            "vertical_slide_in_tab_length": "4",
            "vertical_slide_in_tab_width": "20",
            "width_of_opening_in_case": "230"
        },
        "Ipad 9th gen touch chat 42": {
            "Braille_location": "above opening",
            "Braille_size_multiplier": "10",
            "Braille_text": "",
            "Braille_to_opening_distance": "5",
            "add_circular_opening": "yes",
            "add_mini_tabs": "no",
            "add_symmetric_openings": "no",
            "approx_dovetail_width": "4",
            "bar_corner_radius": "2",
            "bar_edge_slope": "90",
            "bottom_edge_compensation_for_tight_cases": "0",
            "bottom_of_status_bar": "1594",
            "bottom_of_upper_command_bar": "1333",
            "bottom_of_upper_message_bar": "1427",
            "bottom_padding": "0",
            "case_height": "220",
            "case_opening_corner_radius": "5",
            "case_thickness": "15",
            "case_to_screen_depth": "5",
            "case_width": "275",
            "cell_bottom_edge_slope": "90",
            "cell_corner_radius": "3",
            "cell_diameter": "15",
            "cell_edge_chamfer": "0.69999999999999996",
            "cell_edge_slope": "90",
            "cell_height": "18",
            "cell_shape": "rectangular",
            "cell_top_edge_slope": "90",
            "cell_width": "25",
            "clip_bottom_length": "35",
            "clip_locations": "horizontal only",
            "cut_out_screen": "no",
            "diameter_of_opening": "10",
            "distance_between_horizontal_clips": "60",
            "distance_between_horizontal_slide_in_tabs": "60",
            "distance_between_raised_tabs": "45",
            "distance_between_vertical_clips": "40",
            "distance_between_vertical_slide_in_tabs": "60",
            "embed_magnets": "no",
            "engraved_text": "",
            "expose_ambient_light_sensors": "yes",
            "expose_camera": "yes",
            "expose_home_button": "yes",
            "expose_lower_command_bar": "no",
            "expose_lower_message_bar": "no",
            "expose_status_bar": "no",
            "expose_upper_command_bar": "no",
            "expose_upper_message_bar": "yes",
            "first_two_layers_only": "no",
            "font_style": "normal",
            "generate": "keyguard",
            "have_a_case": "yes",
            "have_a_keyguard_frame": "no",
            "height_of_opening_in_case": "158",
            "height_of_ridge": "2",
            "home_button_edge_slope": "30",
            "horizontal_clip_width": "20",
            "horizontal_rail_width": "5",
            "horizontal_slide_in_tab_length": "4",
            "horizontal_slide_in_tab_width": "20",
            "include_screenshot": "no",
            "insert_recess": "0",
            "insert_tightness_of_fit": "0",
            "keyguard_corner_radius": "2",
            "keyguard_display_angle": "0",
            "keyguard_edge_chamfer": "0.69999999999999996",
            "keyguard_frame_thickness": "5",
            "keyguard_height": "178",
            "keyguard_horizontal_tightness_of_fit": "0",
            "keyguard_location": "top surface",
            "keyguard_region": "screen region",
            "keyguard_thickness": "4",
            "keyguard_vertical_tightness_of_fit": "0",
            "keyguard_width": "210",
            "left_edge_compensation_for_tight_cases": "2",
            "left_padding": "0",
            "lower_command_bar_height": "0",
            "lower_message_bar_height": "0",
            "magnet_size": "20 x 8 x 1.5",
            "mini_tab_height": "1",
            "mini_tab_inset_distance": "20",
            "mini_tab_length": "2",
            "mini_tab_width": "10",
            "mount_keyguard_with": "snap-in tabs",
            "mount_to_top_of_opening_distance": "5",
            "mounting_method": "Raised Tabs",
            "move_screenshot_horizontally": "0",
            "move_screenshot_vertically": "0",
            "notch_in_post": "yes",
            "number_of_columns": "7",
            "number_of_rows": "6",
            "orientation": "landscape",
            "post_diameter": "4",
            "post_length": "5",
            "post_tightness_of_fit": "0",
            "preferred_rail_height": "4",
            "preferred_raised_tab_thickness": "3",
            "preferred_slide_in_tab_thickness": "2",
            "rail_slope": "90",
            "raised_tab_height": "5",
            "raised_tab_length": "25",
            "raised_tab_width": "23",
            "ramp_angle": "45",
            "right_edge_compensation_for_tight_cases": "2",
            "right_padding": "0",
            "screen_area_thickness": "4",
            "shelf_depth": "3",
            "shelf_thickness": "2",
            "show_back_of_keyguard": "no",
            "slide_horizontally": "0",
            "slide_in_tab_locations": "horizontal only",
            "slide_vertically": "0",
            "smoothness_of_circles_and_arcs": "40",
            "snap_in_tab_on_bottom_edge_of_keyguard": "yes",
            "snap_in_tab_on_top_edge_of_keyguard": "yes",
            "split_line": "0",
            "split_line_location": "0",
            "split_line_type": "flat",
            "starting_corner_for_screen_measurements": "upper-left",
            "starting_height": "0",
            "status_bar_height": "0",
            "swap_camera_and_home_button": "no",
            "text": "",
            "text_angle": "horizontal",
            "text_depth": "-2",
            "text_height": "5",
            "text_horizontal_alignment": "center",
            "text_vertical_alignment": "center",
            "thickness_of_ridge": "2",
            "tightness_of_dovetail_joint": "5",
            "top_edge_compensation_for_tight_cases": "0",
            "top_of_lower_command_bar": "0",
            "top_of_lower_message_bar": "0",
            "top_padding": "0",
            "trim_to_screen": "no",
            "type_of_keyguard": "3D-Printed",
            "type_of_tablet": "iPad 9th generation",
            "unequal_bottom_side_of_case": "0",
            "unequal_bottom_side_of_case_opening": "0",
            "unequal_left_side_of_case": "0",
            "unequal_left_side_of_case_opening": "0",
            "unit_of_measure_for_screen": "px",
            "upper_command_bar_height": "0",
            "upper_message_bar_height": "0",
            "use_Laser_Cutting_best_practices": "yes",
            "use_velcro_dots": "yes",
            "velcro_size": "2",
            "vertical_clip_width": "20",
            "vertical_rail_width": "5",
            "vertical_slide_in_tab_length": "4",
            "vertical_slide_in_tab_width": "20",
            "width_of_opening_in_case": "209"
        },
        "Ipad 9th gen less case touch chat 42": {
            "Braille_location": "above opening",
            "Braille_size_multiplier": "10",
            "Braille_text": "",
            "Braille_to_opening_distance": "5",
            "add_circular_opening": "yes",
            "add_mini_tabs": "no",
            "add_symmetric_openings": "no",
            "approx_dovetail_width": "4",
            "bar_corner_radius": "2",
            "bar_edge_slope": "90",
            "bottom_edge_compensation_for_tight_cases": "0",
            "bottom_of_status_bar": "1594",
            "bottom_of_upper_command_bar": "1333",
            "bottom_of_upper_message_bar": "1427",
            "bottom_padding": "0",
            "case_height": "220",
            "case_opening_corner_radius": "5",
            "case_thickness": "15",
            "case_to_screen_depth": "5",
            "case_width": "275",
            "cell_bottom_edge_slope": "90",
            "cell_corner_radius": "3",
            "cell_diameter": "15",
            "cell_edge_chamfer": "0.69999999999999996",
            "cell_edge_slope": "90",
            "cell_height": "18",
            "cell_shape": "rectangular",
            "cell_top_edge_slope": "90",
            "cell_width": "25",
            "clip_bottom_length": "35",
            "clip_locations": "horizontal only",
            "cut_out_screen": "no",
            "diameter_of_opening": "10",
            "distance_between_horizontal_clips": "60",
            "distance_between_horizontal_slide_in_tabs": "60",
            "distance_between_raised_tabs": "45",
            "distance_between_vertical_clips": "40",
            "distance_between_vertical_slide_in_tabs": "60",
            "embed_magnets": "no",
            "engraved_text": "",
            "expose_ambient_light_sensors": "yes",
            "expose_camera": "yes",
            "expose_home_button": "yes",
            "expose_lower_command_bar": "no",
            "expose_lower_message_bar": "no",
            "expose_status_bar": "no",
            "expose_upper_command_bar": "no",
            "expose_upper_message_bar": "yes",
            "first_two_layers_only": "no",
            "font_style": "normal",
            "generate": "keyguard",
            "have_a_case": "yes",
            "have_a_keyguard_frame": "no",
            "height_of_opening_in_case": "160",
            "height_of_ridge": "2",
            "home_button_edge_slope": "30",
            "horizontal_clip_width": "20",
            "horizontal_rail_width": "5",
            "horizontal_slide_in_tab_length": "4",
            "horizontal_slide_in_tab_width": "20",
            "include_screenshot": "no",
            "insert_recess": "0",
            "insert_tightness_of_fit": "0",
            "keyguard_corner_radius": "2",
            "keyguard_display_angle": "0",
            "keyguard_edge_chamfer": "0.69999999999999996",
            "keyguard_frame_thickness": "5",
            "keyguard_height": "178",
            "keyguard_horizontal_tightness_of_fit": "0",
            "keyguard_location": "top surface",
            "keyguard_region": "screen region",
            "keyguard_thickness": "4",
            "keyguard_vertical_tightness_of_fit": "0",
            "keyguard_width": "210",
            "left_edge_compensation_for_tight_cases": "2",
            "left_padding": "0",
            "lower_command_bar_height": "0",
            "lower_message_bar_height": "0",
            "magnet_size": "20 x 8 x 1.5",
            "mini_tab_height": "1",
            "mini_tab_inset_distance": "20",
            "mini_tab_length": "2",
            "mini_tab_width": "10",
            "mount_keyguard_with": "snap-in tabs",
            "mount_to_top_of_opening_distance": "5",
            "mounting_method": "Clip-on Straps",
            "move_screenshot_horizontally": "0",
            "move_screenshot_vertically": "0",
            "notch_in_post": "yes",
            "number_of_columns": "7",
            "number_of_rows": "6",
            "orientation": "landscape",
            "post_diameter": "4",
            "post_length": "5",
            "post_tightness_of_fit": "0",
            "preferred_rail_height": "4",
            "preferred_raised_tab_thickness": "3",
            "preferred_slide_in_tab_thickness": "2",
            "rail_slope": "90",
            "raised_tab_height": "5",
            "raised_tab_length": "25",
            "raised_tab_width": "23",
            "ramp_angle": "45",
            "right_edge_compensation_for_tight_cases": "2",
            "right_padding": "0",
            "screen_area_thickness": "4",
            "shelf_depth": "3",
            "shelf_thickness": "2",
            "show_back_of_keyguard": "no",
            "slide_horizontally": "0",
            "slide_in_tab_locations": "horizontal only",
            "slide_vertically": "0",
            "smoothness_of_circles_and_arcs": "40",
            "snap_in_tab_on_bottom_edge_of_keyguard": "yes",
            "snap_in_tab_on_top_edge_of_keyguard": "yes",
            "split_line": "0",
            "split_line_location": "0",
            "split_line_type": "flat",
            "starting_corner_for_screen_measurements": "upper-left",
            "starting_height": "0",
            "status_bar_height": "0",
            "swap_camera_and_home_button": "no",
            "text": "",
            "text_angle": "horizontal",
            "text_depth": "-2",
            "text_height": "5",
            "text_horizontal_alignment": "center",
            "text_vertical_alignment": "center",
            "thickness_of_ridge": "2",
            "tightness_of_dovetail_joint": "5",
            "top_edge_compensation_for_tight_cases": "0",
            "top_of_lower_command_bar": "0",
            "top_of_lower_message_bar": "0",
            "top_padding": "0",
            "trim_to_screen": "no",
            "type_of_keyguard": "3D-Printed",
            "type_of_tablet": "iPad 9th generation",
            "unequal_bottom_side_of_case": "0",
            "unequal_bottom_side_of_case_opening": "0",
            "unequal_left_side_of_case": "0",
            "unequal_left_side_of_case_opening": "0",
            "unit_of_measure_for_screen": "px",
            "upper_command_bar_height": "0",
            "upper_message_bar_height": "0",
            "use_Laser_Cutting_best_practices": "yes",
            "use_velcro_dots": "yes",
            "velcro_size": "2",
            "vertical_clip_width": "20",
            "vertical_rail_width": "5",
            "vertical_slide_in_tab_length": "4",
            "vertical_slide_in_tab_width": "20",
            "width_of_opening_in_case": "238"
        },
        "Ipad 12.9 6thgen 4gridw": {
            "Braille_location": "above opening",
            "Braille_size_multiplier": "10",
            "Braille_text": "",
            "Braille_to_opening_distance": "5",
            "add_circular_opening": "yes",
            "add_mini_tabs": "no",
            "add_symmetric_openings": "no",
            "approx_dovetail_width": "4",
            "bar_corner_radius": "2",
            "bar_edge_slope": "90",
            "bottom_edge_compensation_for_tight_cases": "0",
            "bottom_of_status_bar": "1700",
            "bottom_of_upper_command_bar": "1700",
            "bottom_of_upper_message_bar": "1700",
            "bottom_padding": "2",
            "case_height": "220",
            "case_opening_corner_radius": "5",
            "case_thickness": "15",
            "case_to_screen_depth": "5",
            "case_width": "275",
            "cell_bottom_edge_slope": "90",
            "cell_corner_radius": "3",
            "cell_diameter": "15",
            "cell_edge_chamfer": "0.69999999999999996",
            "cell_edge_slope": "90",
            "cell_height": "67",
            "cell_shape": "rectangular",
            "cell_top_edge_slope": "90",
            "cell_width": "100",
            "clip_bottom_length": "35",
            "clip_locations": "horizontal and vertical",
            "cut_out_screen": "no",
            "diameter_of_opening": "10",
            "distance_between_horizontal_clips": "60",
            "distance_between_horizontal_slide_in_tabs": "60",
            "distance_between_raised_tabs": "45",
            "distance_between_vertical_clips": "40",
            "distance_between_vertical_slide_in_tabs": "60",
            "embed_magnets": "no",
            "engraved_text": "",
            "expose_ambient_light_sensors": "yes",
            "expose_camera": "yes",
            "expose_home_button": "yes",
            "expose_lower_command_bar": "no",
            "expose_lower_message_bar": "no",
            "expose_status_bar": "no",
            "expose_upper_command_bar": "no",
            "expose_upper_message_bar": "no",
            "first_two_layers_only": "no",
            "font_style": "normal",
            "generate": "keyguard",
            "have_a_case": "yes",
            "have_a_keyguard_frame": "no",
            "height_of_opening_in_case": "196",
            "height_of_ridge": "2",
            "home_button_edge_slope": "30",
            "horizontal_clip_width": "20",
            "horizontal_rail_width": "5",
            "horizontal_slide_in_tab_length": "4",
            "horizontal_slide_in_tab_width": "20",
            "include_screenshot": "yes",
            "insert_recess": "0",
            "insert_tightness_of_fit": "0",
            "keyguard_corner_radius": "2",
            "keyguard_display_angle": "0",
            "keyguard_edge_chamfer": "0.69999999999999996",
            "keyguard_frame_thickness": "5",
            "keyguard_height": "178",
            "keyguard_horizontal_tightness_of_fit": "0",
            "keyguard_location": "top surface",
            "keyguard_region": "screen region",
            "keyguard_thickness": "4",
            "keyguard_vertical_tightness_of_fit": "0",
            "keyguard_width": "210",
            "left_edge_compensation_for_tight_cases": "0",
            "left_padding": "10",
            "lower_command_bar_height": "0",
            "lower_message_bar_height": "0",
            "magnet_size": "20 x 8 x 1.5",
            "mini_tab_height": "1",
            "mini_tab_inset_distance": "20",
            "mini_tab_length": "2",
            "mini_tab_width": "10",
            "mount_keyguard_with": "snap-in tabs",
            "mount_to_top_of_opening_distance": "5",
            "mounting_method": "Clip-on Straps",
            "move_screenshot_horizontally": "0",
            "move_screenshot_vertically": "0",
            "notch_in_post": "yes",
            "number_of_columns": "2",
            "number_of_rows": "2",
            "orientation": "landscape",
            "post_diameter": "4",
            "post_length": "5",
            "post_tightness_of_fit": "0",
            "preferred_rail_height": "4",
            "preferred_raised_tab_thickness": "3",
            "preferred_slide_in_tab_thickness": "2",
            "rail_slope": "90",
            "raised_tab_height": "5",
            "raised_tab_length": "25",
            "raised_tab_width": "23",
            "ramp_angle": "45",
            "right_edge_compensation_for_tight_cases": "0",
            "right_padding": "10",
            "screen_area_thickness": "4",
            "shelf_depth": "3",
            "shelf_thickness": "2",
            "show_back_of_keyguard": "no",
            "slide_horizontally": "0",
            "slide_in_tab_locations": "horizontal only",
            "slide_vertically": "0",
            "smoothness_of_circles_and_arcs": "40",
            "snap_in_tab_on_bottom_edge_of_keyguard": "yes",
            "snap_in_tab_on_top_edge_of_keyguard": "yes",
            "split_line": "0",
            "split_line_location": "0",
            "split_line_type": "flat",
            "starting_corner_for_screen_measurements": "upper-left",
            "starting_height": "0",
            "status_bar_height": "0",
            "swap_camera_and_home_button": "no",
            "text": "",
            "text_angle": "horizontal",
            "text_depth": "-2",
            "text_height": "5",
            "text_horizontal_alignment": "center",
            "text_vertical_alignment": "center",
            "thickness_of_ridge": "2",
            "tightness_of_dovetail_joint": "5",
            "top_edge_compensation_for_tight_cases": "0",
            "top_of_lower_command_bar": "0",
            "top_of_lower_message_bar": "0",
            "top_padding": "-2",
            "trim_to_screen": "no",
            "type_of_keyguard": "3D-Printed",
            "type_of_tablet": "iPad Pro 12.9-inch 6th Generation",
            "unequal_bottom_side_of_case": "0",
            "unequal_bottom_side_of_case_opening": "0",
            "unequal_left_side_of_case": "0",
            "unequal_left_side_of_case_opening": "0",
            "unit_of_measure_for_screen": "px",
            "upper_command_bar_height": "0",
            "upper_message_bar_height": "0",
            "use_Laser_Cutting_best_practices": "yes",
            "use_velcro_dots": "yes",
            "velcro_size": "2",
            "vertical_clip_width": "20",
            "vertical_rail_width": "5",
            "vertical_slide_in_tab_length": "4",
            "vertical_slide_in_tab_width": "20",
            "width_of_opening_in_case": "263"
        },
        "Ipad 9th gen less case touch chat 42 with clip": {
            "Braille_location": "above opening",
            "Braille_size_multiplier": "10",
            "Braille_text": "",
            "Braille_to_opening_distance": "5",
            "add_circular_opening": "yes",
            "add_mini_tabs": "no",
            "add_symmetric_openings": "no",
            "approx_dovetail_width": "4",
            "bar_corner_radius": "2",
            "bar_edge_slope": "90",
            "bottom_edge_compensation_for_tight_cases": "0",
            "bottom_of_status_bar": "1594",
            "bottom_of_upper_command_bar": "1333",
            "bottom_of_upper_message_bar": "1427",
            "bottom_padding": "0",
            "case_height": "220",
            "case_opening_corner_radius": "5",
            "case_thickness": "15",
            "case_to_screen_depth": "5",
            "case_width": "275",
            "cell_bottom_edge_slope": "90",
            "cell_corner_radius": "3",
            "cell_diameter": "15",
            "cell_edge_chamfer": "0.69999999999999996",
            "cell_edge_slope": "90",
            "cell_height": "18",
            "cell_shape": "rectangular",
            "cell_top_edge_slope": "90",
            "cell_width": "25",
            "clip_bottom_length": "35",
            "clip_locations": "vertical only",
            "cut_out_screen": "no",
            "diameter_of_opening": "10",
            "distance_between_horizontal_clips": "60",
            "distance_between_horizontal_slide_in_tabs": "60",
            "distance_between_raised_tabs": "45",
            "distance_between_vertical_clips": "40",
            "distance_between_vertical_slide_in_tabs": "60",
            "embed_magnets": "no",
            "engraved_text": "",
            "expose_ambient_light_sensors": "yes",
            "expose_camera": "yes",
            "expose_home_button": "yes",
            "expose_lower_command_bar": "no",
            "expose_lower_message_bar": "no",
            "expose_status_bar": "no",
            "expose_upper_command_bar": "no",
            "expose_upper_message_bar": "yes",
            "first_two_layers_only": "no",
            "font_style": "normal",
            "generate": "keyguard",
            "have_a_case": "yes",
            "have_a_keyguard_frame": "no",
            "height_of_opening_in_case": "160",
            "height_of_ridge": "2",
            "home_button_edge_slope": "30",
            "horizontal_clip_width": "20",
            "horizontal_rail_width": "5",
            "horizontal_slide_in_tab_length": "4",
            "horizontal_slide_in_tab_width": "20",
            "include_screenshot": "no",
            "insert_recess": "0",
            "insert_tightness_of_fit": "0",
            "keyguard_corner_radius": "2",
            "keyguard_display_angle": "0",
            "keyguard_edge_chamfer": "0.69999999999999996",
            "keyguard_frame_thickness": "5",
            "keyguard_height": "178",
            "keyguard_horizontal_tightness_of_fit": "0",
            "keyguard_location": "top surface",
            "keyguard_region": "screen region",
            "keyguard_thickness": "4",
            "keyguard_vertical_tightness_of_fit": "0",
            "keyguard_width": "210",
            "left_edge_compensation_for_tight_cases": "2",
            "left_padding": "0",
            "lower_command_bar_height": "0",
            "lower_message_bar_height": "0",
            "magnet_size": "20 x 8 x 1.5",
            "mini_tab_height": "1",
            "mini_tab_inset_distance": "20",
            "mini_tab_length": "2",
            "mini_tab_width": "10",
            "mount_keyguard_with": "snap-in tabs",
            "mount_to_top_of_opening_distance": "5",
            "mounting_method": "Clip-on Straps",
            "move_screenshot_horizontally": "0",
            "move_screenshot_vertically": "0",
            "notch_in_post": "yes",
            "number_of_columns": "7",
            "number_of_rows": "6",
            "orientation": "landscape",
            "post_diameter": "4",
            "post_length": "5",
            "post_tightness_of_fit": "0",
            "preferred_rail_height": "4",
            "preferred_raised_tab_thickness": "3",
            "preferred_slide_in_tab_thickness": "2",
            "rail_slope": "90",
            "raised_tab_height": "5",
            "raised_tab_length": "25",
            "raised_tab_width": "23",
            "ramp_angle": "45",
            "right_edge_compensation_for_tight_cases": "2",
            "right_padding": "0",
            "screen_area_thickness": "4",
            "shelf_depth": "3",
            "shelf_thickness": "2",
            "show_back_of_keyguard": "no",
            "slide_horizontally": "0",
            "slide_in_tab_locations": "horizontal only",
            "slide_vertically": "0",
            "smoothness_of_circles_and_arcs": "40",
            "snap_in_tab_on_bottom_edge_of_keyguard": "yes",
            "snap_in_tab_on_top_edge_of_keyguard": "yes",
            "split_line": "0",
            "split_line_location": "0",
            "split_line_type": "flat",
            "starting_corner_for_screen_measurements": "upper-left",
            "starting_height": "0",
            "status_bar_height": "0",
            "swap_camera_and_home_button": "no",
            "text": "",
            "text_angle": "horizontal",
            "text_depth": "-2",
            "text_height": "5",
            "text_horizontal_alignment": "center",
            "text_vertical_alignment": "center",
            "thickness_of_ridge": "2",
            "tightness_of_dovetail_joint": "5",
            "top_edge_compensation_for_tight_cases": "0",
            "top_of_lower_command_bar": "0",
            "top_of_lower_message_bar": "0",
            "top_padding": "0",
            "trim_to_screen": "no",
            "type_of_keyguard": "3D-Printed",
            "type_of_tablet": "iPad 9th generation",
            "unequal_bottom_side_of_case": "0",
            "unequal_bottom_side_of_case_opening": "0",
            "unequal_left_side_of_case": "0",
            "unequal_left_side_of_case_opening": "0",
            "unit_of_measure_for_screen": "px",
            "upper_command_bar_height": "0",
            "upper_message_bar_height": "0",
            "use_Laser_Cutting_best_practices": "yes",
            "use_velcro_dots": "yes",
            "velcro_size": "2",
            "vertical_clip_width": "20",
            "vertical_rail_width": "5",
            "vertical_slide_in_tab_length": "4",
            "vertical_slide_in_tab_width": "20",
            "width_of_opening_in_case": "238"
        },
        "Ipad 9th gen touch chat 15": {
            "Braille_location": "above opening",
            "Braille_size_multiplier": "10",
            "Braille_text": "",
            "Braille_to_opening_distance": "5",
            "add_circular_opening": "yes",
            "add_mini_tabs": "no",
            "add_symmetric_openings": "no",
            "approx_dovetail_width": "4",
            "bar_corner_radius": "2",
            "bar_edge_slope": "90",
            "bottom_edge_compensation_for_tight_cases": "0",
            "bottom_of_status_bar": "1594",
            "bottom_of_upper_command_bar": "1333",
            "bottom_of_upper_message_bar": "1427",
            "bottom_padding": "0",
            "case_height": "220",
            "case_opening_corner_radius": "5",
            "case_thickness": "15",
            "case_to_screen_depth": "5",
            "case_width": "275",
            "cell_bottom_edge_slope": "90",
            "cell_corner_radius": "3",
            "cell_diameter": "15",
            "cell_edge_chamfer": "0.69999999999999996",
            "cell_edge_slope": "90",
            "cell_height": "35",
            "cell_shape": "rectangular",
            "cell_top_edge_slope": "90",
            "cell_width": "35",
            "clip_bottom_length": "35",
            "clip_locations": "horizontal only",
            "cut_out_screen": "no",
            "diameter_of_opening": "10",
            "distance_between_horizontal_clips": "60",
            "distance_between_horizontal_slide_in_tabs": "60",
            "distance_between_raised_tabs": "45",
            "distance_between_vertical_clips": "40",
            "distance_between_vertical_slide_in_tabs": "60",
            "embed_magnets": "no",
            "engraved_text": "",
            "expose_ambient_light_sensors": "yes",
            "expose_camera": "yes",
            "expose_home_button": "yes",
            "expose_lower_command_bar": "no",
            "expose_lower_message_bar": "no",
            "expose_status_bar": "no",
            "expose_upper_command_bar": "no",
            "expose_upper_message_bar": "yes",
            "first_two_layers_only": "no",
            "font_style": "normal",
            "generate": "keyguard",
            "have_a_case": "yes",
            "have_a_keyguard_frame": "no",
            "height_of_opening_in_case": "158",
            "height_of_ridge": "2",
            "home_button_edge_slope": "30",
            "horizontal_clip_width": "20",
            "horizontal_rail_width": "5",
            "horizontal_slide_in_tab_length": "4",
            "horizontal_slide_in_tab_width": "20",
            "include_screenshot": "yes",
            "insert_recess": "0",
            "insert_tightness_of_fit": "0",
            "keyguard_corner_radius": "2",
            "keyguard_display_angle": "0",
            "keyguard_edge_chamfer": "0.69999999999999996",
            "keyguard_frame_thickness": "5",
            "keyguard_height": "178",
            "keyguard_horizontal_tightness_of_fit": "0",
            "keyguard_location": "top surface",
            "keyguard_region": "screen region",
            "keyguard_thickness": "4",
            "keyguard_vertical_tightness_of_fit": "0",
            "keyguard_width": "210",
            "left_edge_compensation_for_tight_cases": "2",
            "left_padding": "0",
            "lower_command_bar_height": "0",
            "lower_message_bar_height": "0",
            "magnet_size": "20 x 8 x 1.5",
            "mini_tab_height": "1",
            "mini_tab_inset_distance": "20",
            "mini_tab_length": "2",
            "mini_tab_width": "10",
            "mount_keyguard_with": "snap-in tabs",
            "mount_to_top_of_opening_distance": "5",
            "mounting_method": "Raised Tabs",
            "move_screenshot_horizontally": "0",
            "move_screenshot_vertically": "0",
            "notch_in_post": "yes",
            "number_of_columns": "5",
            "number_of_rows": "3",
            "orientation": "landscape",
            "post_diameter": "4",
            "post_length": "5",
            "post_tightness_of_fit": "0",
            "preferred_rail_height": "4",
            "preferred_raised_tab_thickness": "3",
            "preferred_slide_in_tab_thickness": "2",
            "rail_slope": "90",
            "raised_tab_height": "5",
            "raised_tab_length": "25",
            "raised_tab_width": "23",
            "ramp_angle": "45",
            "right_edge_compensation_for_tight_cases": "2",
            "right_padding": "0",
            "screen_area_thickness": "4",
            "shelf_depth": "3",
            "shelf_thickness": "2",
            "show_back_of_keyguard": "no",
            "slide_horizontally": "0",
            "slide_in_tab_locations": "horizontal only",
            "slide_vertically": "0",
            "smoothness_of_circles_and_arcs": "40",
            "snap_in_tab_on_bottom_edge_of_keyguard": "yes",
            "snap_in_tab_on_top_edge_of_keyguard": "yes",
            "split_line": "0",
            "split_line_location": "0",
            "split_line_type": "flat",
            "starting_corner_for_screen_measurements": "upper-left",
            "starting_height": "0",
            "status_bar_height": "0",
            "swap_camera_and_home_button": "no",
            "text": "",
            "text_angle": "horizontal",
            "text_depth": "-2",
            "text_height": "5",
            "text_horizontal_alignment": "center",
            "text_vertical_alignment": "center",
            "thickness_of_ridge": "2",
            "tightness_of_dovetail_joint": "5",
            "top_edge_compensation_for_tight_cases": "0",
            "top_of_lower_command_bar": "0",
            "top_of_lower_message_bar": "0",
            "top_padding": "0",
            "trim_to_screen": "no",
            "type_of_keyguard": "3D-Printed",
            "type_of_tablet": "iPad 9th generation",
            "unequal_bottom_side_of_case": "0",
            "unequal_bottom_side_of_case_opening": "0",
            "unequal_left_side_of_case": "0",
            "unequal_left_side_of_case_opening": "0",
            "unit_of_measure_for_screen": "px",
            "upper_command_bar_height": "0",
            "upper_message_bar_height": "0",
            "use_Laser_Cutting_best_practices": "yes",
            "use_velcro_dots": "yes",
            "velcro_size": "2",
            "vertical_clip_width": "20",
            "vertical_rail_width": "5",
            "vertical_slide_in_tab_length": "4",
            "vertical_slide_in_tab_width": "20",
            "width_of_opening_in_case": "209"
        }
    }
}
